py_utah_deq/__init__.py
py_utah_deq/utah_deq.py
py_utah_deq/aqi/__init__.py
py_utah_deq/aqi/aqi_metric.py
py_utah_deq/aqi/qualitative_metrics.py
py_utah_deq/data_sources/__init__.py
py_utah_deq/data_sources/utah_deq_api.py
py_utah_deq-0.2.1.dist-info/LICENSE
py_utah_deq-0.2.1.dist-info/METADATA
py_utah_deq-0.2.1.dist-info/WHEEL
py_utah_deq-0.2.1.dist-info/top_level.txt
py_utah_deq-0.2.1.dist-info/RECORD
